CONTRIBUTING.rst
HISTORY.rst
LICENSE
MANIFEST.in
README.md
requirements.pip
setup.cfg
setup.py
bin/.DS_Store
bin/gitberg
gitenberg/.DS_Store
gitenberg/__init__.py
gitenberg/__init__.pyc
gitenberg/actions.py
gitenberg/actions.pyc
gitenberg/book.py
gitenberg/book.pyc
gitenberg/book_identity.py
gitenberg/book_identity.pyc
gitenberg/clone.py
gitenberg/clone.pyc
gitenberg/config.py
gitenberg/config.pyc
gitenberg/dialog.py
gitenberg/dialog.pyc
gitenberg/fetch.py
gitenberg/fetch.pyc
gitenberg/library.py
gitenberg/library.pyc
gitenberg/make.py
gitenberg/make.pyc
gitenberg/pg_wikipedia.py
gitenberg/pg_wikipedia.pyc
gitenberg/push.py
gitenberg/push.pyc
gitenberg/workflow.py
gitenberg/workflow.pyc
gitenberg/data/.DS_Store
gitenberg/data/GITenberg_repo_list.tsv
gitenberg/data/gutenberg_descriptions.json
gitenberg/gitenberg/.DS_Store
gitenberg/gitenberg/__init__.py
gitenberg/gitenberg/__init__.pyc
gitenberg/metadata/__init__.py
gitenberg/metadata/__init__.pyc
gitenberg/metadata/licenses.py
gitenberg/metadata/licenses.pyc
gitenberg/metadata/marc.py
gitenberg/metadata/marc.pyc
gitenberg/metadata/pandata.py
gitenberg/metadata/pandata.pyc
gitenberg/metadata/parameters.py
gitenberg/metadata/parameters.pyc
gitenberg/metadata/pg_rdf.py
gitenberg/metadata/pg_rdf.pyc
gitenberg/metadata/utils.py
gitenberg/metadata/utils.pyc
gitenberg/templates/CONTRIBUTING.rst
gitenberg/templates/LICENSE
gitenberg/templates/README.rst.j2
gitenberg/tests/.DS_Store
gitenberg/tests/__init__.py
gitenberg/tests/__init__.pyc
gitenberg/tests/test_book.py
gitenberg/tests/test_book.pyc
gitenberg/tests/test_config.py
gitenberg/tests/test_config.pyc
gitenberg/tests/test_fetch.py
gitenberg/tests/test_fetch.pyc
gitenberg/tests/test_make.py
gitenberg/tests/test_make.pyc
gitenberg/tests/test_metadata.py
gitenberg/tests/test_metadata.pyc
gitenberg/tests/test_old_metadata.py
gitenberg/tests/test_old_metadata.pyc
gitenberg/tests/test_data/.DS_Store
gitenberg/tests/test_data/1234/pg1234.rdf
xgitberg.egg-info/PKG-INFO
xgitberg.egg-info/SOURCES.txt
xgitberg.egg-info/dependency_links.txt
xgitberg.egg-info/requires.txt
xgitberg.egg-info/top_level.txt