Metadata-Version: 1.1
Name: xgitberg
Version: 0.2.4
Summary: A library and command for interacting with the GITenberg books project
Home-page: https://github.com/gitenberg-dev/gitberg
Author: Seth Woodworth
Author-email: seth@sethish.com
License:                     GNU GENERAL PUBLIC LICENSE
